qnlp/__init__.py
qnlp-0.0.0.dist-info/LICENSE
qnlp-0.0.0.dist-info/METADATA
qnlp-0.0.0.dist-info/WHEEL
qnlp-0.0.0.dist-info/top_level.txt
qnlp-0.0.0.dist-info/RECORD
